untrusted-0.1b2.dist-info/zip-safe
untrusted-0.1b2.dist-info/WHEEL
untrusted-0.1b2.dist-info/METADATA
untrusted-0.1b2.dist-info/metadata.json
untrusted-0.1b2.dist-info/top_level.txt
untrusted-0.1b2.dist-info/DESCRIPTION.rst
untrusted-0.1b2.dist-info/RECORD
untrusted/__init__.py
untrusted/sequence.py
untrusted/util.py
untrusted/iterator.py
untrusted/string.py
untrusted/mapping.py
