Metadata-Version: 2.0
Name: untrusted
Version: 0.1b2
Summary: Wrapper types for untrusted input
Home-page: https://github.com/tawesoft/untrusted.py
Author: Tawesoft Ltd
Author-email: opensource@tawesoft.co.uk
License: MIT
Platform: UNKNOWN
Classifier: Development Status :: 4 - Beta
Classifier: Intended Audience :: Developers
Classifier: License :: OSI Approved :: MIT License
Classifier: Programming Language :: Python :: 3
Classifier: Programming Language :: Python :: 3.4
Classifier: Topic :: Software Development :: Libraries :: Python Modules
Classifier: Topic :: Text Processing :: Filters
